ssrjson_benchmark/__init__.py
ssrjson_benchmark/__main__.py
ssrjson_benchmark/_ssrjson_benchmark.pyd
ssrjson_benchmark/benchmark_impl.py
ssrjson_benchmark/result_types.py
ssrjson_benchmark/template.md
ssrjson_benchmark/_files/apache.json
ssrjson_benchmark/_files/canada.json
ssrjson_benchmark/_files/ctm.json
ssrjson_benchmark/_files/github.json
ssrjson_benchmark/_files/instruments.json
ssrjson_benchmark/_files/mesh.json
ssrjson_benchmark/_files/simple_object.json
ssrjson_benchmark/_files/simple_object_zh.json
ssrjson_benchmark/_files/truenull.json
ssrjson_benchmark/_files/tweet.json
ssrjson_benchmark/_files/twitter.json
ssrjson_benchmark-0.0.10.dist-info/licenses/LICENSE
ssrjson_benchmark-0.0.10.dist-info/METADATA
ssrjson_benchmark-0.0.10.dist-info/WHEEL
ssrjson_benchmark-0.0.10.dist-info/top_level.txt
ssrjson_benchmark-0.0.10.dist-info/RECORD
