Metadata-Version: 2.4
Name: ssrjson-benchmark
Version: 0.0.10
Summary: benchmark of ssrJSON
Author-email: Eritque Arcus <eritque-arcus@ikuyo.dev>, Antares <antares0982@gmail.com>
License-Expression: MIT
Project-URL: Homepage, https://github.com/Nambers/ssrJSON-benchmark
Project-URL: Issues, https://github.com/Nambers/ssrJSON-benchmark/issues
Project-URL: Repository, https://github.com/Nambers/ssrJSON-benchmark.git
Keywords: ssrjson,benchmark,json
Classifier: Development Status :: 5 - Production/Stable
Classifier: Environment :: Console
Classifier: Intended Audience :: Developers
Classifier: Topic :: System :: Benchmark
Classifier: Programming Language :: Python :: 3
Classifier: Operating System :: OS Independent
Requires-Python: >=3.10
License-File: LICENSE
Requires-Dist: ssrjson>=0.0.10
Requires-Dist: orjson
Requires-Dist: msgspec
Requires-Dist: ujson
Requires-Dist: matplotlib
Requires-Dist: psutil
Requires-Dist: svglib
Requires-Dist: reportlab
Requires-Dist: py-cpuinfo
Dynamic: license-file
